impyrialtuto/__init__.py
impyrialtuto/utils.py
impyrialtuto/length/__init__.py
impyrialtuto/length/api.py
impyrialtuto/length/core.py
impyrialtuto/weight/__init__.py
impyrialtuto/weight/api.py
impyrialtuto/weight/core.py
impyrialtuto-0.1.0.dist-info/LICENSE
impyrialtuto-0.1.0.dist-info/METADATA
impyrialtuto-0.1.0.dist-info/WHEEL
impyrialtuto-0.1.0.dist-info/top_level.txt
impyrialtuto-0.1.0.dist-info/RECORD
